rate_exchange_fetcher/__init__.py
rate_exchange_fetcher/client.py
rate_exchange_fetcher/fetcher.py
rate_exchange_fetcher-0.0.4.dist-info/WHEEL
rate_exchange_fetcher-0.0.4.dist-info/METADATA
rate_exchange_fetcher-0.0.4.dist-info/RECORD
